lry_timer/__init__.py
lry_timer-0.0.5.dist-info/LICENSE
lry_timer-0.0.5.dist-info/METADATA
lry_timer-0.0.5.dist-info/WHEEL
lry_timer-0.0.5.dist-info/top_level.txt
lry_timer-0.0.5.dist-info/RECORD
